snakemake_storage_plugin_sharepoint/__init__.py
snakemake_storage_plugin_sharepoint/object.py
snakemake_storage_plugin_sharepoint/provider.py
snakemake_storage_plugin_sharepoint/settings.py
snakemake_storage_plugin_sharepoint-0.4.4.dist-info/licenses/LICENSE
snakemake_storage_plugin_sharepoint-0.4.4.dist-info/WHEEL
snakemake_storage_plugin_sharepoint-0.4.4.dist-info/METADATA
snakemake_storage_plugin_sharepoint-0.4.4.dist-info/RECORD
